CHANGES.rst
MANIFEST.in
README.rst
setup.py
mauritstestpackage/__init__.py
mauritstestpackage.egg-info/PKG-INFO
mauritstestpackage.egg-info/SOURCES.txt
mauritstestpackage.egg-info/dependency_links.txt
mauritstestpackage.egg-info/entry_points.txt
mauritstestpackage.egg-info/not-zip-safe
mauritstestpackage.egg-info/top_level.txt