Metadata-Version: 1.1
Name: mauritstestpackage
Version: 1.18
Summary: Test package from Maurits for uploading to PyPI.
Home-page: https://pypi.python.org/pypi/mauritstestpackage
Author: Maurits van Rees
Author-email: maurits@vanrees.org
License: GPL
Keywords: test release pypi
Platform: UNKNOWN
Classifier: Development Status :: 3 - Alpha
Classifier: Intended Audience :: Developers
Classifier: Programming Language :: Python
Classifier: Programming Language :: Python :: 2
Classifier: Programming Language :: Python :: 2.7
Classifier: Programming Language :: Python :: 3
Classifier: Programming Language :: Python :: 3.4
